mdformat_footnote/__init__.py
mdformat_footnote/_helpers.py
mdformat_footnote/_reorder.py
mdformat_footnote/plugin.py
mdformat_footnote-0.1.3.dist-info/entry_points.txt
mdformat_footnote-0.1.3.dist-info/licenses/LICENSE
mdformat_footnote-0.1.3.dist-info/WHEEL
mdformat_footnote-0.1.3.dist-info/METADATA
mdformat_footnote-0.1.3.dist-info/RECORD
