Metadata-Version: 2.4
Name: mdformat_footnote
Version: 0.1.3
Summary: An mdformat plugin for parsing/validating footnotes
Home-page: https://github.com/gaige/mdformat-footnote
Keywords: mdformat,markdown,markdown-it
Author: Gaige B. Paulsen
Author-email: gaige@cluetrust.com
Requires-Python: >=3.10
Classifier: Development Status :: 4 - Beta
Classifier: Intended Audience :: Developers
Classifier: Environment :: Plugins
Classifier: License :: OSI Approved :: MIT License
Classifier: Programming Language :: Python :: 3
Classifier: Topic :: Software Development :: Libraries :: Python Modules
License-File: LICENSE
Requires-Dist: mdformat >=0.7.0
Requires-Dist: mdit-py-plugins >=0.4.0
Requires-Dist: pre-commit ; extra == "dev"
Requires-Dist: pytest>=8.0.0 ; extra == "test"
Requires-Dist: pytest-cov>=7.0.0 ; extra == "test"
Provides-Extra: dev
Provides-Extra: test
